circlink/__init__.py
circlink/backend.py
circlink/ledger.py
circlink/link.py
circlink/cli/__init__.py
circlink/cli/config.py
circlink/cli/workspace.py
circlink/templates/settings.yaml
circlink-3.3.4.dist-info/LICENSE
circlink-3.3.4.dist-info/METADATA
circlink-3.3.4.dist-info/WHEEL
circlink-3.3.4.dist-info/entry_points.txt
circlink-3.3.4.dist-info/top_level.txt
circlink-3.3.4.dist-info/RECORD
