Metadata-Version: 2.1
Name: circlink
Version: 3.3.4
Summary: Tool for writing code locally and auto-pushing to CircuitPython boards
Author-email: Alec Delaney <tekktrik@gmail.com>
License: MIT
Project-URL: Homepage, https://github.com/tekktrik/circlink.git
Keywords: adafruit,circuitpython,tool,autosave,autopush,circlink,bridge
Classifier: Intended Audience :: Developers
Classifier: Topic :: Software Development :: Embedded Systems
Classifier: Topic :: System :: Hardware
Classifier: License :: OSI Approved :: MIT License
Classifier: Programming Language :: Python :: 3.8
Classifier: Programming Language :: Python :: 3.9
Classifier: Programming Language :: Python :: 3.10
Classifier: Programming Language :: Python :: 3.11
Classifier: Programming Language :: Python :: 3.12
Classifier: Operating System :: Unix
Requires-Python: >=3.8.0
License-File: LICENSE
Requires-Dist: circup ~=1.0
Requires-Dist: psutil ~=5.9
Requires-Dist: pyyaml ~=6.0
Requires-Dist: tabulate ~=0.8
Requires-Dist: typer ~=0.6
Requires-Dist: typing-extensions ~=4.0
Provides-Extra: dev
Requires-Dist: pre-commit ~=3.6 ; extra == 'dev'
Requires-Dist: sphinx ~=7.2 ; extra == 'dev'
Requires-Dist: sphinx-rtd-theme ~=2.0 ; extra == 'dev'
